predict_v2_mk/__init__.py
predict_v2_mk/modelv111.h5
predict_v2_mk/new_data1.txt
predict_v2_mk/predict.py
predict_v2_mk-0.3.dist-info/METADATA
predict_v2_mk-0.3.dist-info/WHEEL
predict_v2_mk-0.3.dist-info/entry_points.txt
predict_v2_mk-0.3.dist-info/top_level.txt
predict_v2_mk-0.3.dist-info/RECORD
