Metadata-Version: 2.1
Name: predict-v2-mk
Version: 0.3
Requires-Dist: numpy
Requires-Dist: tensorflow ==2.12.0
